trytond/modules/health_icu/COPYING
trytond/modules/health_icu/README.rst
trytond/modules/health_icu/__init__.py
trytond/modules/health_icu/data/messages/messages.xml
trytond/modules/health_icu/exceptions.py
trytond/modules/health_icu/health_icu.py
trytond/modules/health_icu/health_icu_view.xml
trytond/modules/health_icu/icons/gnuhealth_icu.svg
trytond/modules/health_icu/locale/ar.po
trytond/modules/health_icu/locale/de.po
trytond/modules/health_icu/locale/el.po
trytond/modules/health_icu/locale/eo.po
trytond/modules/health_icu/locale/es.po
trytond/modules/health_icu/locale/fr.po
trytond/modules/health_icu/locale/health_icu.pot
trytond/modules/health_icu/locale/it_IT.po
trytond/modules/health_icu/locale/ja_JP.po
trytond/modules/health_icu/locale/ka.po
trytond/modules/health_icu/locale/lo.po
trytond/modules/health_icu/locale/pt_BR.po
trytond/modules/health_icu/locale/sv.po
trytond/modules/health_icu/locale/tr.po
trytond/modules/health_icu/locale/uk.po
trytond/modules/health_icu/locale/vi.po
trytond/modules/health_icu/locale/zh_CN.po
trytond/modules/health_icu/pyproject.toml
trytond/modules/health_icu/security/access_rights.xml
trytond/modules/health_icu/tests/__init__.py
trytond/modules/health_icu/tests/test_health_icu.py
trytond/modules/health_icu/tryton.cfg
trytond/modules/health_icu/view/gnuhealth_icu_apache2_form.xml
trytond/modules/health_icu/view/gnuhealth_icu_apache2_tree.xml
trytond/modules/health_icu/view/gnuhealth_icu_chest_drainage_form.xml
trytond/modules/health_icu/view/gnuhealth_icu_chest_drainage_tree.xml
trytond/modules/health_icu/view/gnuhealth_icu_glasgow_form.xml
trytond/modules/health_icu/view/gnuhealth_icu_glasgow_tree.xml
trytond/modules/health_icu/view/gnuhealth_icu_ventilation_form.xml
trytond/modules/health_icu/view/gnuhealth_icu_ventilation_tree.xml
trytond/modules/health_icu/view/gnuhealth_inpatient_icu_form.xml
trytond/modules/health_icu/view/gnuhealth_inpatient_icu_tree.xml
gnuhealth_icu-5.0.2.dist-info/METADATA
gnuhealth_icu-5.0.2.dist-info/WHEEL
gnuhealth_icu-5.0.2.dist-info/licenses/COPYING
gnuhealth_icu-5.0.2.dist-info/RECORD
